igniter/__init__.py
igniter/builder.py
igniter/cli.py
igniter/events.py
igniter/logger.py
igniter/main.py
igniter/registry.py
igniter/utils.py
igniter/visualizer.py
igniter/configs/config.yaml
igniter/datasets/__init__.py
igniter/datasets/coco.py
igniter/datasets/s3_dataset.py
igniter/defaults/__init__.py
igniter/defaults/defaults.py
igniter/defaults/inference_runner.py
igniter/engine/__init__.py
igniter/engine/inference_engine.py
igniter/engine/trainer_engine.py
igniter/engine/utils.py
igniter/io/__init__.py
igniter/io/ignite_logger.py
igniter/io/logger_handles.py
igniter/io/s3_client.py
igniter/io/s3_io.py
igniter/io/s3_utils.py
igniter/io/summary.py
igniter-1.0.13.dist-info/METADATA
igniter-1.0.13.dist-info/WHEEL
igniter-1.0.13.dist-info/entry_points.txt
igniter-1.0.13.dist-info/top_level.txt
igniter-1.0.13.dist-info/zip-safe
igniter-1.0.13.dist-info/RECORD
