Metadata-Version: 2.4
Name: igniter
Version: 1.0.13
Home-page: https://github.com/iKrishneel/igniter
Author: Krishneel
License: MIT
Classifier: Development Status :: 4 - Beta
Classifier: Intended Audience :: Developers
Classifier: Topic :: Software Development :: Build Tools
Classifier: License :: OSI Approved :: MIT License
Classifier: Programming Language :: Python :: 3
Classifier: Programming Language :: Python :: 3.9
Classifier: Programming Language :: Python :: 3.10
Classifier: Programming Language :: Python :: 3.11
Requires-Dist: einops
Requires-Dist: numpy>=1.2
Requires-Dist: matplotlib
Requires-Dist: opencv-python
Requires-Dist: tqdm
Requires-Dist: hydra-core>=1.2
Requires-Dist: tabulate
Requires-Dist: omegaconf
Requires-Dist: colorlog
Requires-Dist: boto3
Requires-Dist: pytest
Requires-Dist: pytest-mock
Requires-Dist: pytorch-ignite>=0.4.12
Requires-Dist: tensorboard
Requires-Dist: argcomplete
Requires-Dist: safetensors
Requires-Dist: requests
Requires-Dist: pycocotools
Dynamic: author
Dynamic: classifier
Dynamic: home-page
Dynamic: license
Dynamic: requires-dist
